 {"result":"true","message":"{\"waterList\":[{\"pageNo\":null,\"pageSize\":null,\"id\":\"777777777\",\"isNewRecord\":false,\"orderBy\":null,\"createByName\":null,\"updateByName\":null,\"updateBy\":null,\"lastUpdateDateTime\":null,\"status\":null,\"createDate\":null,\"updateDate\":null,\"remarks\":null,\"createBy\":null,\"fid\":\"777777777\",\"fengitemcode\":\"02000\",\"fusedvalue\":35333.5533,\"fshowtime\":\"2020-08-11 11:09:20\",\"finserttime\":null,\"fnote\":null,\"fengitemname\":\"总用水\",\"updateDate_gte\":null,\"createDate_between\":null,\"status_in\":null,\"updateDate_between\":null,\"createDate_gte\":null,\"createDate_lte\":null,\"updateDate_lte\":null,\"id_in\":null},{\"pageNo\":null,\"pageSize\":null,\"id\":\"111111125\",\"isNewRecord\":false,\"orderBy\":null,\"createByName\":null,\"updateByName\":null,\"updateBy\":null,\"lastUpdateDateTime\":null,\"status\":null,\"createDate\":null,\"updateDate\":null,\"remarks\":null,\"createBy\":null,\"fid\":\"111111125\",\"fengitemcode\":\"02A00\",\"fusedvalue\":23245.3321,\"fshowtime\":\"2020-08-11 13:40:41\",\"finserttime\":null,\"fnote\":null,\"fengitemname\":\"消防用水\",\"updateDate_gte\":null,\"createDate_between\":null,\"status_in\":null,\"updateDate_between\":null,\"createDate_gte\":null,\"createDate_lte\":null,\"updateDate_lte\":null,\"id_in\":null},{\"pageNo\":null,\"pageSize\":null,\"id\":\"111111126\",\"isNewRecord\":false,\"orderBy\":null,\"createByName\":null,\"updateByName\":null,\"updateBy\":null,\"lastUpdateDateTime\":null,\"status\":null,\"createDate\":null,\"updateDate\":null,\"remarks\":null,\"createBy\":null,\"fid\":\"111111126\",\"fengitemcode\":\"02B00\",\"fusedvalue\":34533.1234,\"fshowtime\":\"2020-08-11 13:41:14\",\"finserttime\":null,\"fnote\":null,\"fengitemname\":\"生活用水\",\"updateDate_gte\":null,\"createDate_between\":null,\"status_in\":null,\"updateDate_between\":null,\"createDate_gte\":null,\"createDate_lte\":null,\"updateDate_lte\":null,\"id_in\":null},{\"pageNo\":null,\"pageSize\":null,\"id\":\"111111127\",\"isNewRecord\":false,\"orderBy\":null,\"createByName\":null,\"updateByName\":null,\"updateBy\":null,\"lastUpdateDateTime\":null,\"status\":null,\"createDate\":null,\"updateDate\":null,\"remarks\":null,\"createBy\":null,\"fid\":\"111111127\",\"fengitemcode\":\"02C00\",\"fusedvalue\":34556.3443,\"fshowtime\":\"2020-08-11 13:41:40\",\"finserttime\":null,\"fnote\":null,\"fengitemname\":\"空调用水\",\"updateDate_gte\":null,\"createDate_between\":null,\"status_in\":null,\"updateDate_between\":null,\"createDate_gte\":null,\"createDate_lte\":null,\"updateDate_lte\":null,\"id_in\":null}],\"electricList\":[{\"pageNo\":null,\"pageSize\":null,\"id\":\"222222222\",\"isNewRecord\":false,\"orderBy\":null,\"createByName\":null,\"updateByName\":null,\"updateBy\":null,\"lastUpdateDateTime\":null,\"status\":null,\"createDate\":null,\"updateDate\":null,\"remarks\":null,\"createBy\":null,\"fid\":\"222222222\",\"fengitemcode\":\"01000\",\"fusedvalue\":3433.1211,\"fshowtime\":\"2020-08-11 10:49:19\",\"finserttime\":null,\"fnote\":null,\"fengitemname\":\"总用电\",\"updateDate_gte\":null,\"createDate_between\":null,\"status_in\":null,\"updateDate_between\":null,\"createDate_gte\":null,\"createDate_lte\":null,\"updateDate_lte\":null,\"id_in\":null},{\"pageNo\":null,\"pageSize\":null,\"id\":\"111111122\",\"isNewRecord\":false,\"orderBy\":null,\"createByName\":null,\"updateByName\":null,\"updateBy\":null,\"lastUpdateDateTime\":null,\"status\":null,\"createDate\":null,\"updateDate\":null,\"remarks\":null,\"createBy\":null,\"fid\":\"111111122\",\"fengitemcode\":\"01K00\",\"fusedvalue\":87433.3322,\"fshowtime\":\"2020-08-11 13:39:04\",\"finserttime\":null,\"fnote\":null,\"fengitemname\":\"充电桩\",\"updateDate_gte\":null,\"createDate_between\":null,\"status_in\":null,\"updateDate_between\":null,\"createDate_gte\":null,\"createDate_lte\":null,\"updateDate_lte\":null,\"id_in\":null},{\"pageNo\":null,\"pageSize\":null,\"id\":\"111111123\",\"isNewRecord\":false,\"orderBy\":null,\"createByName\":null,\"updateByName\":null,\"updateBy\":null,\"lastUpdateDateTime\":null,\"status\":null,\"createDate\":null,\"updateDate\":null,\"remarks\":null,\"createBy\":null,\"fid\":\"111111123\",\"fengitemcode\":\"01L00\",\"fusedvalue\":88782.3232,\"fshowtime\":\"2020-08-11 13:39:41\",\"finserttime\":null,\"fnote\":null,\"fengitemname\":\"供热系统\",\"updateDate_gte\":null,\"createDate_between\":null,\"status_in\":null,\"updateDate_between\":null,\"createDate_gte\":null,\"createDate_lte\":null,\"updateDate_lte\":null,\"id_in\":null},{\"pageNo\":null,\"pageSize\":null,\"id\":\"111111124\",\"isNewRecord\":false,\"orderBy\":null,\"createByName\":null,\"updateByName\":null,\"updateBy\":null,\"lastUpdateDateTime\":null,\"status\":null,\"createDate\":null,\"updateDate\":null,\"remarks\":null,\"createBy\":null,\"fid\":\"111111124\",\"fengitemcode\":\"01N00\",\"fusedvalue\":97223.3221,\"fshowtime\":\"2020-08-11 13:40:10\",\"finserttime\":null,\"fnote\":null,\"fengitemname\":\"其他\",\"updateDate_gte\":null,\"createDate_between\":null,\"status_in\":null,\"updateDate_between\":null,\"createDate_gte\":null,\"createDate_lte\":null,\"updateDate_lte\":null,\"id_in\":null},{\"pageNo\":null,\"pageSize\":null,\"id\":\"111111121\",\"isNewRecord\":false,\"orderBy\":null,\"createByName\":null,\"updateByName\":null,\"updateBy\":null,\"lastUpdateDateTime\":null,\"status\":null,\"createDate\":null,\"updateDate\":null,\"remarks\":null,\"createBy\":null,\"fid\":\"111111121\",\"fengitemcode\":\"01J00\",\"fusedvalue\":90282.2111,\"fshowtime\":\"2020-08-11 13:38:36\",\"finserttime\":null,\"fnote\":null,\"fengitemname\":\"捷运系统\",\"updateDate_gte\":null,\"createDate_between\":null,\"status_in\":null,\"updateDate_between\":null,\"createDate_gte\":null,\"createDate_lte\":null,\"updateDate_lte\":null,\"id_in\":null},{\"pageNo\":null,\"pageSize\":null,\"id\":\"111111113\",\"isNewRecord\":false,\"orderBy\":null,\"createByName\":null,\"updateByName\":null,\"updateBy\":null,\"lastUpdateDateTime\":null,\"status\":null,\"createDate\":null,\"updateDate\":null,\"remarks\":null,\"createBy\":null,\"fid\":\"111111113\",\"fengitemcode\":\"01B00\",\"fusedvalue\":33453.2365,\"fshowtime\":\"2020-08-11 11:18:11\",\"finserttime\":null,\"fnote\":null,\"fengitemname\":\"照明、插座\",\"updateDate_gte\":null,\"createDate_between\":null,\"status_in\":null,\"updateDate_between\":null,\"createDate_gte\":null,\"createDate_lte\":null,\"updateDate_lte\":null,\"id_in\":null},{\"pageNo\":null,\"pageSize\":null,\"id\":\"111111112\",\"isNewRecord\":false,\"orderBy\":null,\"createByName\":null,\"updateByName\":null,\"updateBy\":null,\"lastUpdateDateTime\":null,\"status\":null,\"createDate\":null,\"updateDate\":null,\"remarks\":null,\"createBy\":null,\"fid\":\"111111112\",\"fengitemcode\":\"01A00\",\"fusedvalue\":23322.2367,\"fshowtime\":\"2020-08-11 11:15:43\",\"finserttime\":null,\"fnote\":null,\"fengitemname\":\"商业\",\"updateDate_gte\":null,\"createDate_between\":null,\"status_in\":null,\"updateDate_between\":null,\"createDate_gte\":null,\"createDate_lte\":null,\"updateDate_lte\":null,\"id_in\":null},{\"pageNo\":null,\"pageSize\":null,\"id\":\"111111114\",\"isNewRecord\":false,\"orderBy\":null,\"createByName\":null,\"updateByName\":null,\"updateBy\":null,\"lastUpdateDateTime\":null,\"status\":null,\"createDate\":null,\"updateDate\":null,\"remarks\":null,\"createBy\":null,\"fid\":\"111111114\",\"fengitemcode\":\"01C00\",\"fusedvalue\":23232.4568,\"fshowtime\":\"2020-08-11 11:18:39\",\"finserttime\":null,\"fnote\":null,\"fengitemname\":\"空调系统\",\"updateDate_gte\":null,\"createDate_between\":null,\"status_in\":null,\"updateDate_between\":null,\"createDate_gte\":null,\"createDate_lte\":null,\"updateDate_lte\":null,\"id_in\":null},{\"pageNo\":null,\"pageSize\":null,\"id\":\"111111115\",\"isNewRecord\":false,\"orderBy\":null,\"createByName\":null,\"updateByName\":null,\"updateBy\":null,\"lastUpdateDateTime\":null,\"status\":null,\"createDate\":null,\"updateDate\":null,\"remarks\":null,\"createBy\":null,\"fid\":\"111111115\",\"fengitemcode\":\"01D00\",\"fusedvalue\":34522.2341,\"fshowtime\":\"2020-08-11 11:19:16\",\"finserttime\":null,\"fnote\":null,\"fengitemname\":\"制冷系统\",\"updateDate_gte\":null,\"createDate_between\":null,\"status_in\":null,\"updateDate_between\":null,\"createDate_gte\":null,\"createDate_lte\":null,\"updateDate_lte\":null,\"id_in\":null},{\"pageNo\":null,\"pageSize\":null,\"id\":\"111111116\",\"isNewRecord\":false,\"orderBy\":null,\"createByName\":null,\"updateByName\":null,\"updateBy\":null,\"lastUpdateDateTime\":null,\"status\":null,\"createDate\":null,\"updateDate\":null,\"remarks\":null,\"createBy\":null,\"fid\":\"111111116\",\"fengitemcode\":\"01E00\",\"fusedvalue\":33542.1232,\"fshowtime\":\"2020-08-11 11:20:57\",\"finserttime\":null,\"fnote\":null,\"fengitemname\":\"普通动力\",\"updateDate_gte\":null,\"createDate_between\":null,\"status_in\":null,\"updateDate_between\":null,\"createDate_gte\":null,\"createDate_lte\":null,\"updateDate_lte\":null,\"id_in\":null},{\"pageNo\":null,\"pageSize\":null,\"id\":\"111111117\",\"isNewRecord\":false,\"orderBy\":null,\"createByName\":null,\"updateByName\":null,\"updateBy\":null,\"lastUpdateDateTime\":null,\"status\":null,\"createDate\":null,\"updateDate\":null,\"remarks\":null,\"createBy\":null,\"fid\":\"111111117\",\"fengitemcode\":\"01F00\",\"fusedvalue\":73743.3321,\"fshowtime\":\"2020-08-11 11:21:22\",\"finserttime\":null,\"fnote\":null,\"fengitemname\":\"行李系统\",\"updateDate_gte\":null,\"createDate_between\":null,\"status_in\":null,\"updateDate_between\":null,\"createDate_gte\":null,\"createDate_lte\":null,\"updateDate_lte\":null,\"id_in\":null},{\"pageNo\":null,\"pageSize\":null,\"id\":\"111111118\",\"isNewRecord\":false,\"orderBy\":null,\"createByName\":null,\"updateByName\":null,\"updateBy\":null,\"lastUpdateDateTime\":null,\"status\":null,\"createDate\":null,\"updateDate\":null,\"remarks\":null,\"createBy\":null,\"fid\":\"111111118\",\"fengitemcode\":\"01G00\",\"fusedvalue\":54856.3332,\"fshowtime\":\"2020-08-11 11:21:49\",\"finserttime\":null,\"fnote\":null,\"fengitemname\":\"桥载系统\",\"updateDate_gte\":null,\"createDate_between\":null,\"status_in\":null,\"updateDate_between\":null,\"createDate_gte\":null,\"createDate_lte\":null,\"updateDate_lte\":null,\"id_in\":null},{\"pageNo\":null,\"pageSize\":null,\"id\":\"111111119\",\"isNewRecord\":false,\"orderBy\":null,\"createByName\":null,\"updateByName\":null,\"updateBy\":null,\"lastUpdateDateTime\":null,\"status\":null,\"createDate\":null,\"updateDate\":null,\"remarks\":null,\"createBy\":null,\"fid\":\"111111119\",\"fengitemcode\":\"01H00\",\"fusedvalue\":23232.2321,\"fshowtime\":\"2020-08-11 13:37:43\",\"finserttime\":null,\"fnote\":null,\"fengitemname\":\"消防系统\",\"updateDate_gte\":null,\"createDate_between\":null,\"status_in\":null,\"updateDate_between\":null,\"createDate_gte\":null,\"createDate_lte\":null,\"updateDate_lte\":null,\"id_in\":null},{\"pageNo\":null,\"pageSize\":null,\"id\":\"111111120\",\"isNewRecord\":false,\"orderBy\":null,\"createByName\":null,\"updateByName\":null,\"updateBy\":null,\"lastUpdateDateTime\":null,\"status\":null,\"createDate\":null,\"updateDate\":null,\"remarks\":null,\"createBy\":null,\"fid\":\"111111120\",\"fengitemcode\":\"01I00\",\"fusedvalue\":54343.2432,\"fshowtime\":\"2020-08-11 13:38:14\",\"finserttime\":null,\"fnote\":null,\"fengitemname\":\"弱电系统\",\"updateDate_gte\":null,\"createDate_between\":null,\"status_in\":null,\"updateDate_between\":null,\"createDate_gte\":null,\"createDate_lte\":null,\"updateDate_lte\":null,\"id_in\":null}]}"}